docs/__init__.py
examples/__init__.py
examples/graph_model_optimization.py
examples/profiler_example.py
examples/synthetic_graph_evolution/__init__.py
examples/synthetic_graph_evolution/abstract_graph_search.py
examples/synthetic_graph_evolution/graph_features.py
examples/synthetic_graph_evolution/graph_metrics.py
examples/synthetic_graph_evolution/mmd.py
examples/synthetic_graph_evolution/utils.py
golem/__init__.py
golem/core/__init__.py
golem/core/constants.py
golem/core/log.py
golem/core/paths.py
golem/core/adapter/__init__.py
golem/core/adapter/adapt_registry.py
golem/core/adapter/adapter.py
golem/core/adapter/nx_adapter.py
golem/core/dag/__init__.py
golem/core/dag/convert.py
golem/core/dag/graph.py
golem/core/dag/graph_delegate.py
golem/core/dag/graph_node.py
golem/core/dag/graph_utils.py
golem/core/dag/graph_verifier.py
golem/core/dag/linked_graph.py
golem/core/dag/linked_graph_node.py
golem/core/dag/verification_rules.py
golem/core/optimisers/__init__.py
golem/core/optimisers/advisor.py
golem/core/optimisers/graph.py
golem/core/optimisers/initial_graphs_generator.py
golem/core/optimisers/opt_node_factory.py
golem/core/optimisers/optimization_parameters.py
golem/core/optimisers/optimizer.py
golem/core/optimisers/populational_optimizer.py
golem/core/optimisers/random_graph_factory.py
golem/core/optimisers/timer.py
golem/core/optimisers/archive/__init__.py
golem/core/optimisers/archive/generation_keeper.py
golem/core/optimisers/archive/individuals_containers.py
golem/core/optimisers/fitness/__init__.py
golem/core/optimisers/fitness/fitness.py
golem/core/optimisers/fitness/multi_objective_fitness.py
golem/core/optimisers/genetic/__init__.py
golem/core/optimisers/genetic/evaluation.py
golem/core/optimisers/genetic/gp_operators.py
golem/core/optimisers/genetic/gp_optimizer.py
golem/core/optimisers/genetic/gp_params.py
golem/core/optimisers/genetic/operators/__init__.py
golem/core/optimisers/genetic/operators/crossover.py
nss_golem-0.1.1.dist-info/LICENSE
nss_golem-0.1.1.dist-info/METADATA
nss_golem-0.1.1.dist-info/WHEEL
nss_golem-0.1.1.dist-info/top_level.txt
nss_golem-0.1.1.dist-info/RECORD
