Metadata-Version: 2.1
Name: nss-golem
Version: 0.1.1
Summary: Framework for Graph Optimization and Learning by Evolutionary Methods
Home-page: https://github.com/aimclub/GOLEM
Author: NSS Lab
Author-email: itmo.nss.team@gmail.com
License: BSD 3-Clause
Classifier: License :: OSI Approved :: BSD License
Classifier: Programming Language :: Python :: 3.7
Classifier: Programming Language :: Python :: 3.8
Classifier: Programming Language :: Python :: 3.9
Requires-Python: >=3.7
License-File: LICENSE
Requires-Dist: numpy (!=1.24.0,>=1.16.*)
Requires-Dist: networkx (!=2.7.*,!=2.8.1,!=2.8.2,!=2.8.3,>=2.4)
Requires-Dist: scipy
Requires-Dist: pyvis (==0.2.1)
Requires-Dist: seaborn (>=0.9.*)
Requires-Dist: func-timeout (==4.3.5)
Requires-Dist: joblib (>=0.17.*)
Requires-Dist: requests (>=2.*)
Requires-Dist: tqdm
Requires-Dist: typing (>=3.7.*)
Requires-Dist: psutil (>=5.9.2)
Requires-Dist: pytest (>=6.2.*)
Requires-Dist: testfixtures (>=6.18.*)
Requires-Dist: pandas (<1.3.0,>=1.1.0) ; python_version == "3.7"
Requires-Dist: matplotlib (==3.0.2) ; python_version == "3.7"
Requires-Dist: pandas (>=1.3.0) ; python_version >= "3.8"
Requires-Dist: matplotlib (>=3.3.1) ; python_version >= "3.8"
Provides-Extra: docs
Requires-Dist: sphinx (==4.2.0) ; extra == 'docs'
Requires-Dist: sphinx-rtd-theme (==1.0.0) ; extra == 'docs'
Requires-Dist: readthedocs-sphinx-search (==0.1.1) ; extra == 'docs'
Requires-Dist: sphinxcontrib-details-directive ; extra == 'docs'
Requires-Dist: autodocsumm ; extra == 'docs'
Provides-Extra: profilers
Requires-Dist: snakeviz (==2.1.0) ; extra == 'profilers'
Requires-Dist: gprof2dot (==2021.2.21) ; extra == 'profilers'
Requires-Dist: objgraph (==3.5.0) ; extra == 'profilers'
Requires-Dist: memory-profiler (==0.58.0) ; extra == 'profilers'
